gaetan_picsou/__init__.py
gaetan_picsou/picsou.py
gaetan_picsou-0.1.0.dist-info/METADATA
gaetan_picsou-0.1.0.dist-info/WHEEL
gaetan_picsou-0.1.0.dist-info/RECORD
