Metadata-Version: 2.1
Name: gaetan-picsou
Version: 0.1.0
Summary: 
Author: Gaëtan Brulin
Author-email: gaetan62950@gmail.com
Requires-Python: >=3.12,<4.0
Classifier: Programming Language :: Python :: 3
Classifier: Programming Language :: Python :: 3.12
Requires-Dist: pillow (>=10.2.0,<11.0.0)
